{"sections": [{"title": "Installation", "path": "/learn/installation", "URL": "https://beta.reactjs.org/learn/installation", "size": 3683, "pages": [{"title": "Start a New React Project", "path": "/learn/start-a-new-react-project", "URL": "https://beta.reactjs.org/learn/start-a-new-react-project", "size": 5508, "pages": []}, {"title": "Add React to a Website", "path": "/learn/add-react-to-a-website", "URL": "https://beta.reactjs.org/learn/add-react-to-a-website", "size": 21077, "pages": []}, {"title": "Editor Setup", "path": "/learn/editor-setup", "URL": "https://beta.reactjs.org/learn/editor-setup", "size": 4541, "pages": []}, {"title": "React Developer Tools", "path": "/learn/react-developer-tools", "URL": "https://beta.reactjs.org/learn/react-developer-tools", "size": 3913, "pages": []}]}, {"title": "Quick Start", "path": "/learn", "URL": "https://beta.reactjs.org/learn", "size": 31867, "pages": [{"title": "Tutorial: Tic-Tac-Toe", "path": "/learn/tutorial-tic-tac-toe", "URL": "https://beta.reactjs.org/learn/tutorial-tic-tac-toe", "size": 217012, "pages": []}, {"title": "Thinking in React", "path": "/learn/thinking-in-react", "URL": "https://beta.reactjs.org/learn/thinking-in-react", "size": 48589, "pages": []}]}, {"title": "Describing the UI", "path": "/learn/describing-the-ui", "URL": "https://beta.reactjs.org/learn/describing-the-ui", "size": 23536, "pages": [{"title": "Your First Component", "path": "/learn/your-first-component", "URL": "https://beta.reactjs.org/learn/your-first-component", "size": 15999, "pages": []}, {"title": "Importing and Exporting Components", "path": "/learn/importing-and-exporting-components", "URL": "https://beta.reactjs.org/learn/importing-and-exporting-components", "size": 14485, "pages": []}, {"title": "Writing Markup with JSX", "path": "/learn/writing-markup-with-jsx", "URL": "https://beta.reactjs.org/learn/writing-markup-with-jsx", "size": 14940, "pages": []}, {"title": "JavaScript in JSX with Curly Braces", "path": "/learn/javascript-in-jsx-with-curly-braces", "URL": "https://beta.reactjs.org/learn/javascript-in-jsx-with-curly-braces", "size": 16234, "pages": []}, {"title": "Passing Props to a Component", "path": "/learn/passing-props-to-a-component", "URL": "https://beta.reactjs.org/learn/passing-props-to-a-component", "size": 25268, "pages": []}, {"title": "Conditional Rendering", "path": "/learn/conditional-rendering", "URL": "https://beta.reactjs.org/learn/conditional-rendering", "size": 31088, "pages": []}, {"title": "Rendering Lists", "path": "/learn/rendering-lists", "URL": "https://beta.reactjs.org/learn/rendering-lists", "size": 26225, "pages": []}, {"title": "Keeping Components Pure", "path": "/learn/keeping-components-pure", "URL": "https://beta.reactjs.org/learn/keeping-components-pure", "size": 20081, "pages": []}]}, {"title": "Adding Interactivity", "path": "/learn/adding-interactivity", "URL": "https://beta.reactjs.org/learn/adding-interactivity", "size": 43516, "pages": [{"title": "Responding to Events", "path": "/learn/responding-to-events", "URL": "https://beta.reactjs.org/learn/responding-to-events", "size": 34263, "pages": []}, {"title": "State: A Component's Memory", "path": "/learn/state-a-components-memory", "URL": "https://beta.reactjs.org/learn/state-a-components-memory", "size": 41521, "pages": []}, {"title": "Render and Commit", "path": "/learn/render-and-commit", "URL": "https://beta.reactjs.org/learn/render-and-commit", "size": 10611, "pages": []}, {"title": "State as a Snapshot", "path": "/learn/state-as-a-snapshot", "URL": "https://beta.reactjs.org/learn/state-as-a-snapshot", "size": 24368, "pages": []}, {"title": "Queueing a Series of State Updates", "path": "/learn/queueing-a-series-of-state-updates", "URL": "https://beta.reactjs.org/learn/queueing-a-series-of-state-updates", "size": 22156, "pages": []}, {"title": "Updating Objects in State", "path": "/learn/updating-objects-in-state", "URL": "https://beta.reactjs.org/learn/updating-objects-in-state", "size": 52630, "pages": []}, {"title": "Updating Arrays in State", "path": "/learn/updating-arrays-in-state", "URL": "https://beta.reactjs.org/learn/updating-arrays-in-state", "size": 59204, "pages": []}]}, {"title": "Managing State", "path": "/learn/managing-state", "URL": "https://beta.reactjs.org/learn/managing-state", "size": 38417, "pages": [{"title": "Reacting to Input with State", "path": "/learn/reacting-to-input-with-state", "URL": "https://beta.reactjs.org/learn/reacting-to-input-with-state", "size": 32892, "pages": []}, {"title": "Choosing the State Structure", "path": "/learn/choosing-the-state-structure", "URL": "https://beta.reactjs.org/learn/choosing-the-state-structure", "size": 86128, "pages": []}, {"title": "Sharing State Between Components", "path": "/learn/sharing-state-between-components", "URL": "https://beta.reactjs.org/learn/sharing-state-between-components", "size": 23382, "pages": []}, {"title": "Preserving and Resetting State", "path": "/learn/preserving-and-resetting-state", "URL": "https://beta.reactjs.org/learn/preserving-and-resetting-state", "size": 61120, "pages": []}, {"title": "Extracting State Logic into a Reducer", "path": "/learn/extracting-state-logic-into-a-reducer", "URL": "https://beta.reactjs.org/learn/extracting-state-logic-into-a-reducer", "size": 50007, "pages": []}, {"title": "Passing Data Deeply with Context", "path": "/learn/passing-data-deeply-with-context", "URL": "https://beta.reactjs.org/learn/passing-data-deeply-with-context", "size": 44487, "pages": []}, {"title": "Scaling Up with Reducer and Context", "path": "/learn/scaling-up-with-reducer-and-context", "URL": "https://beta.reactjs.org/learn/scaling-up-with-reducer-and-context", "size": 41080, "pages": []}]}, {"title": "Escape Hatches", "path": "/learn/escape-hatches", "URL": "https://beta.reactjs.org/learn/escape-hatches", "size": 47177, "pages": [{"title": "Referencing Values with Refs", "path": "/learn/referencing-values-with-refs", "URL": "https://beta.reactjs.org/learn/referencing-values-with-refs", "size": 25658, "pages": []}, {"title": "Manipulating the DOM with Refs", "path": "/learn/manipulating-the-dom-with-refs", "URL": "https://beta.reactjs.org/learn/manipulating-the-dom-with-refs", "size": 48440, "pages": []}, {"title": "Synchronizing with Effects", "path": "/learn/synchronizing-with-effects", "URL": "https://beta.reactjs.org/learn/synchronizing-with-effects", "size": 79430, "pages": []}, {"title": "You Might Not Need an Effect", "path": "/learn/you-might-not-need-an-effect", "URL": "https://beta.reactjs.org/learn/you-might-not-need-an-effect", "size": 83929, "pages": []}, {"title": "Lifecycle of Reactive Effects", "path": "/learn/lifecycle-of-reactive-effects", "URL": "https://beta.reactjs.org/learn/lifecycle-of-reactive-effects", "size": 66911, "pages": []}, {"title": "Separating Events from Effects", "path": "/learn/separating-events-from-effects", "URL": "https://beta.reactjs.org/learn/separating-events-from-effects", "size": 68722, "pages": []}, {"title": "Removing Effect Dependencies", "path": "/learn/removing-effect-dependencies", "URL": "https://beta.reactjs.org/learn/removing-effect-dependencies", "size": 98333, "pages": []}, {"title": "Reusing Logic with Custom Hooks", "path": "/learn/reusing-logic-with-custom-hooks", "URL": "https://beta.reactjs.org/learn/reusing-logic-with-custom-hooks", "size": 94963, "pages": []}]}, {"title": "Community", "path": "/community", "URL": "https://beta.reactjs.org/community", "size": 2827, "pages": [{"title": "React Conferences", "path": "/community/conferences", "URL": "https://beta.reactjs.org/community/conferences", "size": 19232, "pages": []}, {"title": "React Meetups", "path": "/community/meetups", "URL": "https://beta.reactjs.org/community/meetups", "size": 6507, "pages": []}, {"title": "React Videos", "path": "/community/videos", "URL": "https://beta.reactjs.org/community/videos", "size": 5380, "pages": []}, {"title": "Meet the Team", "path": "/community/team", "URL": "https://beta.reactjs.org/community/team", "size": 10936, "pages": []}, {"title": "Docs Contributors", "path": "/community/docs-contributors", "URL": "https://beta.reactjs.org/community/docs-contributors", "size": 2096, "pages": []}, {"title": "Acknowledgements", "path": "/community/acknowledgements", "URL": "https://beta.reactjs.org/community/acknowledgements", "size": 3167, "pages": []}, {"title": "Versioning Policy", "path": "/community/versioning-policy", "URL": "https://beta.reactjs.org/community/versioning-policy", "size": 15544, "pages": []}]}, {"title": "Blog", "path": "/blog", "URL": "https://beta.reactjs.org/blog", "size": 4589, "pages": [{"title": "React Labs: June 2022", "path": "/blog/2022/06/15/react-labs-what-we-have-been-working-on-june-2022", "URL": "https://beta.reactjs.org/blog/2022/06/15/react-labs-what-we-have-been-working-on-june-2022", "size": 10486, "pages": []}, {"title": "React v18.0", "path": "/blog/2022/03/29/react-v18", "URL": "https://beta.reactjs.org/blog/2022/03/29/react-v18", "size": 31466, "pages": []}, {"title": "How to Upgrade to React 18", "path": "/blog/2022/03/08/react-18-upgrade-guide", "URL": "https://beta.reactjs.org/blog/2022/03/08/react-18-upgrade-guide", "size": 27769, "pages": []}, {"title": "React Conf 2021 Recap", "path": "/blog/2021/12/17/react-conf-2021-recap", "URL": "https://beta.reactjs.org/blog/2021/12/17/react-conf-2021-recap", "size": 10478, "pages": []}, {"title": "The Plan for React 18", "path": "/blog/2021/06/08/the-plan-for-react-18", "URL": "https://beta.reactjs.org/blog/2021/06/08/the-plan-for-react-18", "size": 6713, "pages": []}, {"title": "Introducing Server Components", "path": "/blog/2020/12/21/data-fetching-with-react-server-components", "URL": "https://beta.reactjs.org/blog/2020/12/21/data-fetching-with-react-server-components", "size": 2273, "pages": []}]}, {"title": "Components", "path": "/reference/react/components", "URL": "https://beta.reactjs.org/reference/react/components", "size": 1906, "pages": [{"title": "<Fragment> (<>)", "path": "/reference/react/Fragment", "URL": "https://beta.reactjs.org/reference/react/Fragment", "size": 13920, "pages": []}, {"title": "<Profiler>", "path": "/reference/react/Profiler", "URL": "https://beta.reactjs.org/reference/react/Profiler", "size": 9383, "pages": []}, {"title": "<StrictMode>", "path": "/reference/react/StrictMode", "URL": "https://beta.reactjs.org/reference/react/StrictMode", "size": 35368, "pages": []}, {"title": "<Suspense>", "path": "/reference/react/Suspense", "URL": "https://beta.reactjs.org/reference/react/Suspense", "size": 45001, "pages": []}]}, {"title": "Hooks", "path": "/reference/react", "URL": "https://beta.reactjs.org/reference/react", "size": 9378, "pages": [{"title": "useCallback", "path": "/reference/react/useCallback", "URL": "https://beta.reactjs.org/reference/react/useCallback", "size": 49481, "pages": []}, {"title": "useContext", "path": "/reference/react/useContext", "URL": "https://beta.reactjs.org/reference/react/useContext", "size": 35949, "pages": []}, {"title": "useDebugValue", "path": "/reference/react/useDebugValue", "URL": "https://beta.reactjs.org/reference/react/useDebugValue", "size": 7023, "pages": []}, {"title": "useDeferredValue", "path": "/reference/react/useDeferredValue", "URL": "https://beta.reactjs.org/reference/react/useDeferredValue", "size": 27695, "pages": []}, {"title": "useEffect", "path": "/reference/react/useEffect", "URL": "https://beta.reactjs.org/reference/react/useEffect", "size": 89265, "pages": []}, {"title": "useId", "path": "/reference/react/useId", "URL": "https://beta.reactjs.org/reference/react/useId", "size": 14540, "pages": []}, {"title": "useImperativeHandle", "path": "/reference/react/useImperativeHandle", "URL": "https://beta.reactjs.org/reference/react/useImperativeHandle", "size": 13551, "pages": []}, {"title": "useInsertionEffect", "path": "/reference/react/useInsertionEffect", "URL": "https://beta.reactjs.org/reference/react/useInsertionEffect", "size": 10009, "pages": []}, {"title": "useLayoutEffect", "path": "/reference/react/useLayoutEffect", "URL": "https://beta.reactjs.org/reference/react/useLayoutEffect", "size": 19824, "pages": []}, {"title": "useMemo", "path": "/reference/react/useMemo", "URL": "https://beta.reactjs.org/reference/react/useMemo", "size": 58005, "pages": []}, {"title": "useReducer", "path": "/reference/react/useReducer", "URL": "https://beta.reactjs.org/reference/react/useReducer", "size": 43776, "pages": []}, {"title": "useRef", "path": "/reference/react/useRef", "URL": "https://beta.reactjs.org/reference/react/useRef", "size": 22057, "pages": []}, {"title": "useState", "path": "/reference/react/useState", "URL": "https://beta.reactjs.org/reference/react/useState", "size": 49715, "pages": []}, {"title": "useSyncExternalStore", "path": "/reference/react/useSyncExternalStore", "URL": "https://beta.reactjs.org/reference/react/useSyncExternalStore", "size": 26796, "pages": []}, {"title": "useTransition", "path": "/reference/react/useTransition", "URL": "https://beta.reactjs.org/reference/react/useTransition", "size": 40866, "pages": []}]}, {"title": "APIs", "path": "/reference/react/apis", "URL": "https://beta.reactjs.org/reference/react/apis", "size": 2119, "pages": [{"title": "createContext", "path": "/reference/react/createContext", "URL": "https://beta.reactjs.org/reference/react/createContext", "size": 14067, "pages": []}, {"title": "forwardRef", "path": "/reference/react/forwardRef", "URL": "https://beta.reactjs.org/reference/react/forwardRef", "size": 26913, "pages": []}, {"title": "lazy", "path": "/reference/react/lazy", "URL": "https://beta.reactjs.org/reference/react/lazy", "size": 11382, "pages": []}, {"title": "memo", "path": "/reference/react/memo", "URL": "https://beta.reactjs.org/reference/react/memo", "size": 29526, "pages": []}, {"title": "startTransition", "path": "/reference/react/startTransition", "URL": "https://beta.reactjs.org/reference/react/startTransition", "size": 6647, "pages": []}]}, {"title": "Components", "path": "/reference/react-dom/components", "URL": "https://beta.reactjs.org/reference/react-dom/components", "size": 12164, "pages": [{"title": "Common (e.g. <div>)", "path": "/reference/react-dom/components/common", "URL": "https://beta.reactjs.org/reference/react-dom/components/common", "size": 83890, "pages": []}, {"title": "<input>", "path": "/reference/react-dom/components/input", "URL": "https://beta.reactjs.org/reference/react-dom/components/input", "size": 43707, "pages": []}, {"title": "<option>", "path": "/reference/react-dom/components/option", "URL": "https://beta.reactjs.org/reference/react-dom/components/option", "size": 5211, "pages": []}, {"title": "<progress>", "path": "/reference/react-dom/components/progress", "URL": "https://beta.reactjs.org/reference/react-dom/components/progress", "size": 4084, "pages": []}, {"title": "<select>", "path": "/reference/react-dom/components/select", "URL": "https://beta.reactjs.org/reference/react-dom/components/select", "size": 29554, "pages": []}, {"title": "<textarea>", "path": "/reference/react-dom/components/textarea", "URL": "https://beta.reactjs.org/reference/react-dom/components/textarea", "size": 25808, "pages": []}]}, {"title": "APIs", "path": "/reference/react-dom", "URL": "https://beta.reactjs.org/reference/react-dom", "size": 2867, "pages": [{"title": "createPortal", "path": "/reference/react-dom/createPortal", "URL": "https://beta.reactjs.org/reference/react-dom/createPortal", "size": 19738, "pages": []}, {"title": "flushSync", "path": "/reference/react-dom/flushSync", "URL": "https://beta.reactjs.org/reference/react-dom/flushSync", "size": 9021, "pages": []}, {"title": "findDOMNode", "path": "/reference/react-dom/findDOMNode", "URL": "https://beta.reactjs.org/reference/react-dom/findDOMNode", "size": 18042, "pages": []}, {"title": "hydrate", "path": "/reference/react-dom/hydrate", "URL": "https://beta.reactjs.org/reference/react-dom/hydrate", "size": 10301, "pages": []}, {"title": "render", "path": "/reference/react-dom/render", "URL": "https://beta.reactjs.org/reference/react-dom/render", "size": 10216, "pages": []}, {"title": "unmountComponentAtNode", "path": "/reference/react-dom/unmountComponentAtNode", "URL": "https://beta.reactjs.org/reference/react-dom/unmountComponentAtNode", "size": 5854, "pages": []}]}, {"title": "Client APIs", "path": "/reference/react-dom/client", "URL": "https://beta.reactjs.org/reference/react-dom/client", "size": 1803, "pages": [{"title": "createRoot", "path": "/reference/react-dom/client/createRoot", "URL": "https://beta.reactjs.org/reference/react-dom/client/createRoot", "size": 22421, "pages": []}, {"title": "hydrateRoot", "path": "/reference/react-dom/client/hydrateRoot", "URL": "https://beta.reactjs.org/reference/react-dom/client/hydrateRoot", "size": 19309, "pages": []}]}, {"title": "Server APIs", "path": "/reference/react-dom/server", "URL": "https://beta.reactjs.org/reference/react-dom/server", "size": 3072, "pages": [{"title": "renderToNodeStream", "path": "/reference/react-dom/server/renderToNodeStream", "URL": "https://beta.reactjs.org/reference/react-dom/server/renderToNodeStream", "size": 4699, "pages": []}, {"title": "renderToPipeableStream", "path": "/reference/react-dom/server/renderToPipeableStream", "URL": "https://beta.reactjs.org/reference/react-dom/server/renderToPipeableStream", "size": 51229, "pages": []}, {"title": "renderToReadableStream", "path": "/reference/react-dom/server/renderToReadableStream", "URL": "https://beta.reactjs.org/reference/react-dom/server/renderToReadableStream", "size": 52244, "pages": []}, {"title": "renderToStaticMarkup", "path": "/reference/react-dom/server/renderToStaticMarkup", "URL": "https://beta.reactjs.org/reference/react-dom/server/renderToStaticMarkup", "size": 4488, "pages": []}, {"title": "renderToStaticNodeStream", "path": "/reference/react-dom/server/renderToStaticNodeStream", "URL": "https://beta.reactjs.org/reference/react-dom/server/renderToStaticNodeStream", "size": 4883, "pages": []}, {"title": "renderToString", "path": "/reference/react-dom/server/renderToString", "URL": "https://beta.reactjs.org/reference/react-dom/server/renderToString", "size": 8515, "pages": []}]}, {"title": "Legacy React APIs", "path": "/reference/react/legacy", "URL": "https://beta.reactjs.org/reference/react/legacy", "size": 2913, "pages": [{"title": "Children", "path": "/reference/react/Children", "URL": "https://beta.reactjs.org/reference/react/Children", "size": 41387, "pages": []}, {"title": "cloneElement", "path": "/reference/react/cloneElement", "URL": "https://beta.reactjs.org/reference/react/cloneElement", "size": 30706, "pages": []}, {"title": "Component", "path": "/reference/react/Component", "URL": "https://beta.reactjs.org/reference/react/Component", "size": 115929, "pages": []}, {"title": "createElement", "path": "/reference/react/createElement", "URL": "https://beta.reactjs.org/reference/react/createElement", "size": 13039, "pages": []}, {"title": "createFactory", "path": "/reference/react/createFactory", "URL": "https://beta.reactjs.org/reference/react/createFactory", "size": 13146, "pages": []}, {"title": "createRef", "path": "/reference/react/createRef", "URL": "https://beta.reactjs.org/reference/react/createRef", "size": 9558, "pages": []}, {"title": "isValidElement", "path": "/reference/react/isValidElement", "URL": "https://beta.reactjs.org/reference/react/isValidElement", "size": 9147, "pages": []}, {"title": "PureComponent", "path": "/reference/react/PureComponent", "URL": "https://beta.reactjs.org/reference/react/PureComponent", "size": 14896, "pages": []}]}]}